invocr/__init__.py
invocr/__main__.py
invocr/api/__init__.py
invocr/api/main.py
invocr/api/models.py
invocr/api/routes.py
invocr/cli/__init__.py
invocr/cli/cli.py
invocr/cli/commands/__init__.py
invocr/cli/commands/batch_command.py
invocr/cli/commands/config_command.py
invocr/cli/commands/convert_command.py
invocr/cli/commands/extract_command.py
invocr/cli/commands/validate_command.py
invocr/cli/commands.py
invocr/cli/common.py
invocr/config/__init__.py
invocr/config/loader.py
invocr/core/__init__.py
invocr/core/converter.py
invocr/core/detection/__init__.py
invocr/core/detection/decision_tree.py
invocr/core/detection/pipeline.py
invocr/core/extractor.py
invocr/core/ocr.py
invocr/core/pdf_processor.py
invocr/core/validator.py
invocr/core/validators/__init__.py
invocr/core/validators/base.py
invocr/core/validators/cross_field.py
invocr/core/validators/document.py
invocr/core/validators/factory.py
invocr/core/validators/items.py
invocr/core/validators/party.py
invocr/core/validators/totals.py
invocr/extractors/__init__.py
invocr/extractors/de/__init__.py
invocr/extractors/de/extractor.py
invocr/extractors/en/__init__.py
invocr/extractors/en/extractor.py
invocr/extractors/es/__init__.py
invocr/extractors/es/extractor.py
invocr/extractors/fr/__init__.py
invocr/extractors/fr/extractor.py
invocr/extractors/pl/__init__.py
invocr/extractors/pl/extractor.py
invocr/extractors/specialized/__init__.py
invocr/extractors/specialized/adobe_extractor.py
invocr/formats/__init__.py
invocr/formats/html_handler.py
invocr/formats/image.py
invocr/formats/json_handler.py
invocr/formats/pdf/__init__.py
invocr/formats/pdf/config/__init__.py
invocr/formats/pdf/config/default_rules.py
invocr/formats/pdf/config/default_rules_fixed.py
invocr/formats/pdf/converter.py
invocr/formats/pdf/document.py
invocr/formats/pdf/document_models.py
invocr/formats/pdf/extractor.py
invocr/formats/pdf/extractor.py.bak
invocr/formats/pdf/extractor_base.py
invocr/formats/pdf/extractors/__init__.py
invocr-1.0.16.dist-info/LICENSE
invocr-1.0.16.dist-info/METADATA
invocr-1.0.16.dist-info/WHEEL
invocr-1.0.16.dist-info/entry_points.txt
invocr-1.0.16.dist-info/RECORD
