Metadata-Version: 2.3
Name: invocr
Version: 1.0.16
Summary: Invoice OCR System - Convert invoices between PDF, JSON, XML, HTML formats using OCR
License: Apache
Author: Tom Sapletta
Author-email: info@softreck.dev
Requires-Python: >=3.9,<4.0
Classifier: License :: Other/Proprietary License
Classifier: Programming Language :: Python :: 3
Classifier: Programming Language :: Python :: 3.9
Classifier: Programming Language :: Python :: 3.10
Classifier: Programming Language :: Python :: 3.11
Classifier: Programming Language :: Python :: 3.12
Classifier: Programming Language :: Python :: 3.13
Requires-Dist: aiofiles (>=23.2.1,<24.0.0)
Requires-Dist: click (>=8.1.7,<9.0.0)
Requires-Dist: easyocr (>=1.7.0,<2.0.0)
Requires-Dist: fastapi (>=0.104.1,<0.105.0)
Requires-Dist: imgkit (>=1.2.3,<2.0.0)
Requires-Dist: invoice2data (>=0.4.5,<0.5.0)
Requires-Dist: jinja2 (>=3.1.2,<4.0.0)
Requires-Dist: jsonschema (>=4.24.0,<5.0.0)
Requires-Dist: loguru (>=0.7.2,<0.8.0)
Requires-Dist: lxml (>=4.9.3,<5.0.0)
Requires-Dist: numpy (>=1.24.3,<2.0.0)
Requires-Dist: opencv-python (>=4.8.1.78,<5.0.0.0)
Requires-Dist: pdf2image (>=1.16.3,<2.0.0)
Requires-Dist: pdfplumber (>=0.9.0,<0.10.0)
Requires-Dist: pillow (>=10.1.0,<11.0.0)
Requires-Dist: pydantic (>=2.5.0,<3.0.0)
Requires-Dist: pydantic-settings (>=2.1.0,<3.0.0)
Requires-Dist: pymupdf (>=1.26.1,<2.0.0)
Requires-Dist: pypdf2 (>=3.0.1,<4.0.0)
Requires-Dist: pytesseract (>=0.3.10,<0.4.0)
Requires-Dist: python-dateutil (>=2.9.0.post0,<3.0.0)
Requires-Dist: python-multipart (>=0.0.6,<0.0.7)
Requires-Dist: rich (>=14.0.0,<15.0.0)
Requires-Dist: tox (>=4.27.0,<5.0.0)
Requires-Dist: transformers (>=4.52.4,<5.0.0)
Requires-Dist: uvicorn[standard] (>=0.24.0,<0.25.0)
Requires-Dist: weasyprint (>=60.2,<61.0)
Project-URL: Documentation, https://invocr.readthedocs.io
Project-URL: Homepage, https://github.com/fin-officer/invocr
Project-URL: Repository, https://github.com/fin-officer/invocr
